{"AB Small Cap Growth Portfolio Holdings": {"long_name": ["Plug Power Inc", "Tetra Tech Inc", "Sleep Number Corp", "Ab Fixed Income Shares, Inc. - Government Money Market Portfolio - Class Ab", "John Bean Technologies Corp", "Silicon Laboratories Inc", "Lattice Semiconductor Corp", "Texas Roadhouse Inc", "Lithia Motors Inc Class A", "II-VI Inc"], "short_name": ["PLUG", "TTEK", "SNBR", "", "JBT", "SLAB", "LSCC", "TXRH", "LAD", "IIVI"], "net_asset": ["1.87", "1.67", "1.66", "1.65", "1.57", "1.54", "1.52", "1.52", "1.50", "1.50"]}, "T. Rowe Price Instl Small-Cap Stock Fund Holdings": {"long_name": ["Boston Beer Co Inc Class A", "Lattice Semiconductor Corp", "Entegris Inc", "Molina Healthcare Inc", "Burlington Stores Inc", "FirstService Corp", "Cable One Inc", "SiteOne Landscape Supply Inc", "Catalent Inc", "Five9 Inc"], "short_name": ["SAM", "LSCC", "ENTG", "MOH", "BURL", "FSV", "CABO", "SITE", "CTLT", "FIVN"], "net_asset": ["1.72", "1.35", "1.35", "1.18", "1.18", "1.12", "1.10", "1.10", "1.06", "1.04"]}, "Fidelity\u00ae Small Cap Growth K6 Fund Holdings": {"long_name": ["Fidelity Revere Str Tr", "Stepstone Cl A(180 Day Lockup)", "Crocs Inc", "Builders FirstSource Inc", "SiTime Corp Ordinary Shares", "Insulet Corp", "Kornit Digital Ltd", "Plug Power Inc", "Caesars Entertainment Inc", "Novavax Inc"], "short_name": ["", "", "CROX", "BLDR", "SITM", "PODD", "KRNT", "PLUG", "CZR", "NVAX"], "net_asset": ["1.68", "1.40", "1.39", "1.37", "1.35", "1.35", "1.11", "1.11", "1.10", "1.06"]}, "Federated Hermes Kaufmann Sm Cp Fd Holdings": {"long_name": ["Federated Hermes Inst Prime Val Obl IS", "Ultragenyx Pharmaceutical Inc", "argenx SE", "Zai Lab Ltd ADR Repr 1 Shs", "Rapid7 Inc", "Natera Inc", "Nuvei Corp Subordinate Vtg Common Stock", "Q2 Holdings Inc", "Planet Fitness Inc A", "Mercury Systems Inc"], "short_name": ["PVOXX", "RARE", "ARGX", "ZLAB", "RPD", "NTRA", "", "QTWO", "PLNT", "MRCY"], "net_asset": ["9.89", "2.04", "1.72", "1.50", "1.06", "1.03", "1.01", "0.98", "0.97", "0.91"]}, "Baron Discovery Fund Holdings": {"long_name": ["TripAdvisor Inc", "Mercury Systems Inc", "TPI Composites Inc", "Endava PLC ADR", "Inogen Inc", "Advanced Energy Industries Inc", "CareDx Inc", "Floor & Decor Holdings Inc", "Kinsale Capital Group Inc", "SiteOne Landscape Supply Inc"], "short_name": ["TRIP", "MRCY", "TPIC", "DAVA", "INGN", "AEIS", "CDNA", "FND", "KNSL", "SITE"], "net_asset": ["2.71", "2.69", "2.42", "2.33", "2.27", "2.13", "2.08", "2.04", "2.01", "1.94"]}, "T. Rowe Price Small-Cap Stock Fund Holdings": {"long_name": ["Boston Beer Co Inc Class A", "Entegris Inc", "Lattice Semiconductor Corp", "Molina Healthcare Inc", "Burlington Stores Inc", "FirstService Corp", "Cable One Inc", "SiteOne Landscape Supply Inc", "Catalent Inc", "Five9 Inc"], "short_name": ["SAM", "ENTG", "LSCC", "MOH", "BURL", "FSV", "CABO", "SITE", "CTLT", "FIVN"], "net_asset": ["1.73", "1.35", "1.33", "1.19", "1.18", "1.12", "1.11", "1.10", "1.05", "1.04"]}, "TCM Small-Cap Growth Fund Holdings": {"long_name": ["Kinsale Capital Group Inc", "Natera Inc", "Asgn Inc", "Element Solutions Inc", "Progyny Inc", "Wns (Holdings) Ltd Adr", "Onto Innovation Inc", "First American Treasury Obligs X", "Spdr\u00ae S&P Biotech Etf", "The Shyft Group Inc"], "short_name": ["KNSL", "NTRA", "ASGN", "ESI", "PGNY", "WNS", "ONTO", "FXFXX", "XBI", "SHYF"], "net_asset": ["3.56", "2.74", "2.14", "2.06", "2.05", "1.92", "1.88", "1.88", "1.87", "1.81"]}, "JPMorgan Small Cap Growth Fund Holdings": {"long_name": ["Advanced Drainage Systems Inc", "Natera Inc", "Itron Inc", "Boyd Gaming Corp", "Freshpet Inc", "John Bean Technologies Corp", "Saia Inc", "Halozyme Therapeutics Inc", "Performance Food Group Co", "JPMorgan Prime Money Market IM"], "short_name": ["WMS", "NTRA", "ITRI", "BYD", "FRPT", "JBT", "SAIA", "HALO", "PFGC", "JIMXX"], "net_asset": ["2.00", "1.93", "1.64", "1.53", "1.51", "1.50", "1.48", "1.46", "1.45", "1.41"]}, "Virtus KAR Small-Cap Growth Fund Holdings": {"long_name": ["Auto Trader Group PLC", "Bill.com Holdings Inc Ordinary Shares", "Autohome Inc ADR", "BlackLine Inc", "Fox Factory Holding Corp", "Ollie's Bargain Outlet Holdings Inc", "Duck Creek Technologies Inc Ordinary Shares", "Rightmove PLC", "MarketAxess Holdings Inc", "Morningstar Inc"], "short_name": ["AUTO", "BILL", "ATHM", "BL", "FOXF", "OLLI", "DCT", "RMV", "MKTX", "MORN"], "net_asset": ["6.38", "6.20", "5.92", "5.64", "5.46", "5.27", "5.08", "4.83", "4.68", "4.56"]}, "Lord Abbett Developing Growth Fund Holdings": {"long_name": ["Inspire Medical Systems Inc", "Sonos Inc", "Natera Inc", "Silvergate Capital Corp Class A", "Digital Turbine Inc", "Axon Enterprise Inc", "Western Alliance Bancorp", "Cardlytics Inc", "RH", "MKS Instruments Inc"], "short_name": ["INSP", "SONO", "NTRA", "SI", "APPS", "AXON", "WAL", "CDLX", "RH", "MKSI"], "net_asset": ["2.23", "1.93", "1.85", "1.83", "1.80", "1.76", "1.66", "1.53", "1.53", "1.52"]}}